post_for_me/__init__.py
post_for_me/_base_client.py
post_for_me/_client.py
post_for_me/_compat.py
post_for_me/_constants.py
post_for_me/_exceptions.py
post_for_me/_files.py
post_for_me/_models.py
post_for_me/_qs.py
post_for_me/_resource.py
post_for_me/_response.py
post_for_me/_streaming.py
post_for_me/_types.py
post_for_me/_version.py
post_for_me/py.typed
post_for_me/_utils/__init__.py
post_for_me/_utils/_compat.py
post_for_me/_utils/_datetime_parse.py
post_for_me/_utils/_logs.py
post_for_me/_utils/_proxy.py
post_for_me/_utils/_reflection.py
post_for_me/_utils/_resources_proxy.py
post_for_me/_utils/_streams.py
post_for_me/_utils/_sync.py
post_for_me/_utils/_transform.py
post_for_me/_utils/_typing.py
post_for_me/_utils/_utils.py
post_for_me/lib/.keep
post_for_me/resources/__init__.py
post_for_me/resources/media.py
post_for_me/resources/social_account_feeds.py
post_for_me/resources/social_accounts.py
post_for_me/resources/social_post_results.py
post_for_me/resources/social_posts.py
post_for_me/types/__init__.py
post_for_me/types/bluesky_configuration_dto.py
post_for_me/types/bluesky_configuration_dto_param.py
post_for_me/types/facebook_configuration_dto.py
post_for_me/types/facebook_configuration_dto_param.py
post_for_me/types/instagram_configuration_dto.py
post_for_me/types/instagram_configuration_dto_param.py
post_for_me/types/linkedin_configuration_dto.py
post_for_me/types/linkedin_configuration_dto_param.py
post_for_me/types/media_create_upload_url_response.py
post_for_me/types/pinterest_configuration_dto.py
post_for_me/types/pinterest_configuration_dto_param.py
post_for_me/types/platform_configurations_dto.py
post_for_me/types/platform_configurations_dto_param.py
post_for_me/types/platform_post.py
post_for_me/types/social_account.py
post_for_me/types/social_account_create_auth_url_params.py
post_for_me/types/social_account_create_auth_url_response.py
post_for_me/types/social_account_create_params.py
post_for_me/types/social_account_disconnect_response.py
post_for_me-1.10.1.dist-info/METADATA
post_for_me-1.10.1.dist-info/WHEEL
post_for_me-1.10.1.dist-info/licenses/LICENSE
post_for_me-1.10.1.dist-info/RECORD
